RevilosLib/CLI.py
RevilosLib/IDgenerator.py
RevilosLib/__init__.py
RevilosLib-0.0.2.dist-info/LICENSE
RevilosLib-0.0.2.dist-info/METADATA
RevilosLib-0.0.2.dist-info/WHEEL
RevilosLib-0.0.2.dist-info/top_level.txt
RevilosLib-0.0.2.dist-info/RECORD
