Metadata-Version: 2.1
Name: RevilosLib
Version: 0.0.2
License: Copyright (c) 2018 The Python Packaging Authority
Project-URL: Homepage, https://github.com/Revilo0509/RevilosLib
Project-URL: Documentation, https://github.com/Revilo0509/RevilosLib/wiki
Project-URL: Issues, https://github.com/Revilo0509/RevilosLib/issues
Classifier: Programming Language :: Python :: 3
Classifier: License :: OSI Approved :: MIT License
Classifier: Operating System :: OS Independent
Requires-Python: >=3.8
License-File: LICENSE
Requires-Dist: keyboard >=0.13.5
